sslbookdata/__init__.py
sslbookdata/sslbookdata.py
sslbookdata/data/data1.mat
sslbookdata/data/data2.mat
sslbookdata/data/data3.mat
sslbookdata/data/data4.mat
sslbookdata/data/data5.mat
sslbookdata/data/data6.mat
sslbookdata/data/data7.mat
sslbookdata/data/data8.mat
sslbookdata/data/data8extra.mat
sslbookdata/data/data9.mat
sslbookdata/data/splits1-labeled10.mat
sslbookdata/data/splits1-labeled100.mat
sslbookdata/data/splits2-labeled10.mat
sslbookdata/data/splits2-labeled100.mat
sslbookdata/data/splits3-labeled10.mat
sslbookdata/data/splits3-labeled100.mat
sslbookdata/data/splits4-labeled10.mat
sslbookdata/data/splits4-labeled100.mat
sslbookdata/data/splits5-labeled10.mat
sslbookdata/data/splits5-labeled100.mat
sslbookdata/data/splits6-labeled10.mat
sslbookdata/data/splits6-labeled100.mat
sslbookdata/data/splits7-labeled10.mat
sslbookdata/data/splits7-labeled100.mat
sslbookdata/data/splits8-labeled100.mat
sslbookdata/data/splits8-labeled1000.mat
sslbookdata/data/splits8-labeled10000.mat
sslbookdata/data/splits9-labeled10.mat
sslbookdata/data/splits9-labeled100.mat
sslbookdata-0.1.dist-info/AUTHORS
sslbookdata-0.1.dist-info/LICENSE
sslbookdata-0.1.dist-info/METADATA
sslbookdata-0.1.dist-info/WHEEL
sslbookdata-0.1.dist-info/top_level.txt
sslbookdata-0.1.dist-info/RECORD
