Metadata-Version: 2.1
Name: sslbookdata
Version: 0.1
Summary: 9 data sets for semi-supervised learning
Home-page: https://bitbucket.org/oliverobst/sslbookdata
Author: Oliver Obst
Author-email: o.obst@westernsydney.edu.au
License: UNKNOWN
Platform: UNKNOWN
Classifier: Programming Language :: Python :: 3
Classifier: License :: OSI Approved :: MIT License
Classifier: Operating System :: OS Independent
Requires-Python: >=3
